{
	"Character_Name": "Kamisato Ayaka",
	"Character_Title": "Frostflake Heron",
	"Embed_Color": "#a0d7e4",
	"Role_Build": [
		{
			"Build_Name": "DPS_Build",
			"Best_Artifacts_4x": [
				"Blizzard Strayer"
			],
			"Best_Artifacts_2x": [
				"Blizzard Strayer (2) +18% ATK set (2)",
				"+18% ATK set (2) +18% ATK set (2)",
				"Blizzard Strayer (2) Noblesse Oblige (2)"
			],
			"Weapon": [
				"Mistsplitter Reforged",
				"Haran Geppaku Futsu",
				"Light of Foliar Incision",
				"Primordial Jade Cutter",
				"Summit Shaper",
				"Finale of the Deep",
				"Aquila Favonia",
				"Skyward Blade",
				"Amenoma Kageuchi",
				"The Black Sword",
				"Kagotsurube Isshin",
				"Harbinger of Dawn"
			],
			"Main_Stats": [
				"Sands: ATK%",
				"Goblet: Cryo DMG%",
				"Circlet: CRIT"
			],
			"Sub_Stats": "ER > CRIT DMG > ATK% >= CRIT Rate"
		},
		{
			"Build_Name": "Support_Build",
			"Best_Artifacts_4x": "You commited a crime",
			"Best_Artifacts_2x": "Imagine using ayaka as support",
			"Weapon": "SMH go use ayaka as dps",
			"Main_Stats": "oof just use her as dps",
			"Sub_Stats": "same"
		}
	],
	"Team_Compositions": "NA",
	"Character_Image_URL": "https://wiki.hoyolab.com/_ipx/f_webp/https://bbs.hoyolab.com/hoyowiki/picture/character/Kamisato%2520Ayaka_icon.png"
}