{
	"Character_Name": "Venti",
	"Character_Title": "Windborne Bard",
	"Embed_Color": "#75c2aa",
	"Role_Build": [
		{
			"Build_Name": "Support_Build",
			"Best_Artifacts_4x": [
				"Viridescent Venerer",
				"Gilded Dreams",
				"Instructor"
			],
			"Best_Artifacts_2x": [
				"Wanderer's Troupe",
				"Instructor"
			],
			"Weapon": [
				"Elegy for the End",
				"The Stringless",
				"Mouun's Moon",
				"Alley Hunter",
				"Windblume Ode",
				"Raven Bow",
				"Fading Twilight",
				"Prototype Crescent",
				"Favonius Warbow"
			],
			"Main_Stats": [
				"Sands: Elemental Mastery",
				"Goblet: Elemental Mastery",
				"Circlet: Elemental Mastery"
			],
			"Sub_Stats": "ER (until sufficient) > EM > ATK% = CR > CD/Flat ATK"
		},
		{
			"Build_Name": "DPS_Build",
			"Best_Artifacts_4x": [
				"Viridescent Venerer",
				"Emblem of Severed Fate"
			],
			"Best_Artifacts_2x": [
				"Viridescent Venerer",
				"Desert Pavilion Chronicle",
				"Noblesse Oblige"
			],
			"Weapon": [
				"Polar Star",
				"The Stringless",
				"Aqua Simulacra",
				"Skyward Harp",
				"Elegy for the End",
				"Hunter's Path",
				"Mouun's Moon",
				"Alley Hunter",
				"Blackcliff Warbow",
				"Thundering Pulse"
			],
			"Main_Stats": [
				"Sands: ATK%",
				"Goblet: Anemo DMG%/ATK%",
				"Circlet: CRIT Rate/CRIT Damage"
			],
			"Sub_Stats": "ER (until sufficient) > CR = CD > ATK% > EM/Flat ATK"
		}
	],
	"Team_Compositions": "",
	"Character_Image_URL": "https://wiki.hoyolab.com/_ipx/f_webp/https://bbs.hoyolab.com/hoyowiki/picture/character/Venti_icon.png"
}